django_unity_asset_server_http_client-0.1.5.dist-info/metadata.json
django_unity_asset_server_http_client-0.1.5.dist-info/RECORD
django_unity_asset_server_http_client-0.1.5.dist-info/WHEEL
django_unity_asset_server_http_client-0.1.5.dist-info/METADATA
django_unity_asset_server_http_client-0.1.5.dist-info/top_level.txt
django_unity_asset_server_http_client-0.1.5.dist-info/zip-safe
django_unity_asset_server_http_client-0.1.5.dist-info/DESCRIPTION.rst
duashttp/__init__.py
duashttp/serializers.py
duashttp/models.py
duashttp/router.py
duashttp/filters.py
duashttp/tests.py
duashttp/admin.py
duashttp/migrations/__init__.py
duashttp/views/__init__.py
duashttp/views/views.pyc
duashttp/views/views.py
duashttp/views/api.py
duashttp/views/api.pyc
duashttp/views/__init__.pyc
duashttp/views/__pycache__/api.cpython-34.pyc
duashttp/views/__pycache__/__init__.cpython-34.pyc
duashttp/views/__pycache__/views.cpython-34.pyc
