Metadata-Version: 2.0
Name: django-unity-asset-server-http-client
Version: 0.1.5
Summary: REST-api bases over unity asset server for some routines.
Home-page: https://github.com/tarvitz/django-unity-asset-server-http-client
Author: Tarvitz
Author-email: tarvitz@blacklibrary.ru
License: MIT License
Download-URL: https://github.com/tarvitz/django-unity-asset-server-http-client/archive/v0.1.5.tar.gz
Platform: OS Independent
Classifier: Environment :: Web Environment
Classifier: Development Status :: 4 - Beta
Classifier: Intended Audience :: Developers
Classifier: License :: OSI Approved :: MIT License
Classifier: Operating System :: OS Independent
Classifier: Programming Language :: Python
Classifier: Framework :: Django
Requires-Dist: django-filter (>=0.8)
Requires-Dist: djangorestframework (>=2.4.3)
